{"tableName":"ORDERS","tableAttributes":{"cardinality":"0","noOfColumns":"5","noOfKeyColumns":"1","recordLength":0,"noOfPages":0,"percentagePages":1,"noOfParents":2,"noOfChildren":0,"dbName":"ERDM_DEL","tsName":"null","createdTime":"2017-02-21 14:34:58.977299","lastAltered":"2017-02-21 14:34:59.101367","lastStatistics":"2017-02-21 19:18:45.84074","remarks":"null"},"columnSchema":[{"name":"ORDERID","remarks":null,"colNo":"0","type":"INTEGER ","length":"4","scale":"0","nulls":"N","keySeq":"1","cardinality":"0"},{"name":"USERID","remarks":null,"colNo":"1","type":"INTEGER ","length":"4","scale":"0","nulls":"N","keySeq":null,"cardinality":"0"},{"name":"POSTID","remarks":null,"colNo":"2","type":"INTEGER ","length":"4","scale":"0","nulls":"N","keySeq":null,"cardinality":"0"},{"name":"POSTTITLE","remarks":null,"colNo":"3","type":"CHAR    ","length":"200","scale":"0","nulls":"N","keySeq":null,"cardinality":"0"},{"name":"TEXT","remarks":null,"colNo":"4","type":"VARCHAR ","length":"4000","scale":"0","nulls":"Y","keySeq":null,"cardinality":"0"}],"indices":[{"name":"SQL170221143459050","clustering":"-1.0","clustered":null,"createdTime":"2017-02-21 14:34:58.977299","lastStatsTime":"2017-02-21 19:18:45.84074","clusterRatio":"100","indexColumnInfoList":null,"ruleType":"P","colNames":"+ORDERID"},{"name":"IX_ORDERS","clustering":"-1.0","clustered":null,"createdTime":"2017-02-21 14:39:02.573608","lastStatsTime":"2017-02-21 19:18:45.84074","clusterRatio":"100","indexColumnInfoList":null,"ruleType":"D","colNames":"+ORDERID+USERID+POSTID"}],"views":[],"relationShips":[{"tableName":"ORDERS","refTableName":"USERS","refSchemaName":"ERDM_DEL","deleteRule":"A","createdTime":"2017-02-21 14:34:59.092134","fkColNames":" USERID             "},{"tableName":"ORDERS","refTableName":"POSTS","refSchemaName":"ERDM_DEL","deleteRule":"A","createdTime":"2017-02-21 14:34:59.102986","fkColNames":" POSTID             "}],"queryNotes":null}